osc_recorder/__init__.py
osc_recorder/base.py
osc_recorder/collector.py
osc_recorder/osc_utils.py
osc_recorder-0.1.5.data/scripts/capture_osc
osc_recorder-0.1.5.data/scripts/osc_to_csv
osc_recorder-0.1.5.data/scripts/replay_osc
osc_recorder-0.1.5.dist-info/LICENSE
osc_recorder-0.1.5.dist-info/METADATA
osc_recorder-0.1.5.dist-info/WHEEL
osc_recorder-0.1.5.dist-info/top_level.txt
osc_recorder-0.1.5.dist-info/RECORD
