Metadata-Version: 2.1
Name: osc-recorder
Version: 0.1.5
Summary: Python scripts to capture and replay OSC packets. Built on top of pyliblo.
Home-page: https://github.com/oishefarhan/osc_recorder
Author: Oishe Farhan
Author-email: oishe.farhan@interaxon.ca
License: MIT license
Keywords: osc_recorder
Platform: UNKNOWN
Classifier: Development Status :: 2 - Pre-Alpha
Classifier: Intended Audience :: Developers
Classifier: License :: OSI Approved :: MIT License
Classifier: Natural Language :: English
Classifier: Programming Language :: Python :: 3.7
Requires-Dist: numpy
